{
  "data": [
    {
      "nodeName": "学校教育",
      "nodeId": "86a500400ccf11eaa67400ff735bba7f",
      "childNode": [
        {
          "nodeName": "计算机",
          "nodeId": "eab3025d0ccf11eaa67400ff735bba7f",
          "childNode": null,
          "index": null,
          "attribute": {
            "id": 3,
            "isDelete": 0,
            "createdTime": "2019-12-06T15:41:21.000+0000",
            "createdBy": "c800d893ded111e9b2c6544810e75499",
            "updateTime": "2019-11-22T10:29:31.000+0000",
            "updateBy": "c800d893ded111e9b2c6544810e75499",
            "pageNum": null,
            "pageSize": null,
            "cateCode": "eab3025d0ccf11eaa67400ff735bba7f",
            "cateName": "计算机",
            "parentCateCode": "86a500400ccf11eaa67400ff735bba7f",
            "level": 2,
            "remark": "1-1",
            "frontCateCode": null,
            "parentCateCodeName": null,
            "goods": null,
            "cateList": null
          }
        },
        {
          "nodeName": "数学",
          "nodeId": "67949bea17fc11eaa870005056c00001",
          "childNode": null,
          "index": null,
          "attribute": {
            "id": 8,
            "isDelete": 0,
            "createdTime": "2019-12-06T15:45:41.000+0000",
            "createdBy": "1",
            "updateTime": "2019-12-06T15:45:41.000+0000",
            "updateBy": "1",
            "pageNum": null,
            "pageSize": null,
            "cateCode": "67949bea17fc11eaa870005056c00001",
            "cateName": "数学",
            "parentCateCode": "86a500400ccf11eaa67400ff735bba7f",
            "level": 2,
            "remark": "1-2",
            "frontCateCode": null,
            "parentCateCodeName": null,
            "goods": null,
            "cateList": null
          }
        }
      ],
      "index": null,
      "attribute": {
        "id": 1,
        "isDelete": 0,
        "createdTime": "2019-12-06T15:41:08.000+0000",
        "createdBy": "c800d893ded111e9b2c6544810e75499",
        "updateTime": "2019-11-22T10:26:43.000+0000",
        "updateBy": "c800d893ded111e9b2c6544810e75499",
        "pageNum": null,
        "pageSize": null,
        "cateCode": "86a500400ccf11eaa67400ff735bba7f",
        "cateName": "学校教育",
        "parentCateCode": "0",
        "level": 1,
        "remark": "1",
        "frontCateCode": null,
        "parentCateCodeName": null,
        "goods": null,
        "cateList": null
      }
    },
    {
      "nodeName": "文学经典",
      "nodeId": "b7e4a9480ccf11eaa67400ff735bba7f",
      "childNode": [
        {
          "nodeName": "中国文学",
          "nodeId": "6062781f159c11ea8a11005056c00001",
          "childNode": null,
          "index": null,
          "attribute": {
            "id": 6,
            "isDelete": 0,
            "createdTime": "2019-12-03T15:13:13.000+0000",
            "createdBy": "1",
            "updateTime": "2019-12-03T15:13:13.000+0000",
            "updateBy": "1",
            "pageNum": null,
            "pageSize": null,
            "cateCode": "6062781f159c11ea8a11005056c00001",
            "cateName": "中国文学",
            "parentCateCode": "b7e4a9480ccf11eaa67400ff735bba7f",
            "level": 2,
            "remark": "2-1",
            "frontCateCode": null,
            "parentCateCodeName": null,
            "goods": null,
            "cateList": null
          }
        },
        {
          "nodeName": "外国文学",
          "nodeId": "68761c25159c11ea8a11005056c00001",
          "childNode": null,
          "index": null,
          "attribute": {
            "id": 7,
            "isDelete": 0,
            "createdTime": "2019-12-03T15:13:27.000+0000",
            "createdBy": "1",
            "updateTime": "2019-12-03T15:13:27.000+0000",
            "updateBy": "1",
            "pageNum": null,
            "pageSize": null,
            "cateCode": "68761c25159c11ea8a11005056c00001",
            "cateName": "外国文学",
            "parentCateCode": "b7e4a9480ccf11eaa67400ff735bba7f",
            "level": 2,
            "remark": "2-2",
            "frontCateCode": null,
            "parentCateCodeName": null,
            "goods": null,
            "cateList": null
          }
        }
      ],
      "index": null,
      "attribute": {
        "id": 2,
        "isDelete": 0,
        "createdTime": "2019-12-03T15:13:37.000+0000",
        "createdBy": "c800d893ded111e9b2c6544810e75499",
        "updateTime": "2019-11-22T10:28:06.000+0000",
        "updateBy": "c800d893ded111e9b2c6544810e75499",
        "pageNum": null,
        "pageSize": null,
        "cateCode": "b7e4a9480ccf11eaa67400ff735bba7f",
        "cateName": "文学经典",
        "parentCateCode": "0",
        "level": 1,
        "remark": "2",
        "frontCateCode": null,
        "parentCateCodeName": null,
        "goods": null,
        "cateList": null
      }
    },
    {
      "nodeName": "政治军事",
      "nodeId": "819d21c31b2111eaa870005056c00001",
      "childNode": [
        {
          "nodeName": "中国政治",
          "nodeId": "96d924711b2111eaa870005056c00001",
          "childNode": null,
          "index": null,
          "attribute": {
            "id": 10,
            "isDelete": 0,
            "createdTime": "2019-12-10T15:49:23.000+0000",
            "createdBy": "1",
            "updateTime": "2019-12-10T15:49:23.000+0000",
            "updateBy": "1",
            "pageNum": null,
            "pageSize": null,
            "cateCode": "96d924711b2111eaa870005056c00001",
            "cateName": "中国政治",
            "parentCateCode": "819d21c31b2111eaa870005056c00001",
            "level": 2,
            "remark": "3-1",
            "frontCateCode": null,
            "parentCateCodeName": null,
            "goods": null,
            "cateList": null
          }
        },
        {
          "nodeName": "世界军事",
          "nodeId": "9db75ce31b2111eaa870005056c00001",
          "childNode": null,
          "index": null,
          "attribute": {
            "id": 11,
            "isDelete": 0,
            "createdTime": "2019-12-10T15:49:35.000+0000",
            "createdBy": "1",
            "updateTime": "2019-12-10T15:49:35.000+0000",
            "updateBy": "1",
            "pageNum": null,
            "pageSize": null,
            "cateCode": "9db75ce31b2111eaa870005056c00001",
            "cateName": "世界军事",
            "parentCateCode": "819d21c31b2111eaa870005056c00001",
            "level": 2,
            "remark": "3-2",
            "frontCateCode": null,
            "parentCateCodeName": null,
            "goods": null,
            "cateList": null
          }
        }
      ],
      "index": null,
      "attribute": {
        "id": 9,
        "isDelete": 0,
        "createdTime": "2019-12-10T15:48:48.000+0000",
        "createdBy": "1",
        "updateTime": "2019-12-10T15:48:48.000+0000",
        "updateBy": "1",
        "pageNum": null,
        "pageSize": null,
        "cateCode": "819d21c31b2111eaa870005056c00001",
        "cateName": "政治军事",
        "parentCateCode": "0",
        "level": 1,
        "remark": "3",
        "frontCateCode": null,
        "parentCateCodeName": null,
        "goods": null,
        "cateList": null
      }
    },
    {
      "nodeName": "传记",
      "nodeId": "024cd6bf1b2211eaa870005056c00001",
      "childNode": [
        {
          "nodeName": "政治人物",
          "nodeId": "178ce6811b2211eaa870005056c00001",
          "childNode": null,
          "index": null,
          "attribute": {
            "id": 13,
            "isDelete": 0,
            "createdTime": "2019-12-10T15:52:59.000+0000",
            "createdBy": "1",
            "updateTime": "2019-12-10T15:52:59.000+0000",
            "updateBy": "1",
            "pageNum": null,
            "pageSize": null,
            "cateCode": "178ce6811b2211eaa870005056c00001",
            "cateName": "政治人物",
            "parentCateCode": "024cd6bf1b2211eaa870005056c00001",
            "level": 2,
            "remark": "4-1",
            "frontCateCode": null,
            "parentCateCodeName": null,
            "goods": null,
            "cateList": null
          }
        },
        {
          "nodeName": "历代帝王",
          "nodeId": "1ed0112f1b2211eaa870005056c00001",
          "childNode": null,
          "index": null,
          "attribute": {
            "id": 14,
            "isDelete": 0,
            "createdTime": "2019-12-10T15:53:11.000+0000",
            "createdBy": "1",
            "updateTime": "2019-12-10T15:53:11.000+0000",
            "updateBy": "1",
            "pageNum": null,
            "pageSize": null,
            "cateCode": "1ed0112f1b2211eaa870005056c00001",
            "cateName": "历代帝王",
            "parentCateCode": "024cd6bf1b2211eaa870005056c00001",
            "level": 2,
            "remark": "4-2",
            "frontCateCode": null,
            "parentCateCodeName": null,
            "goods": null,
            "cateList": null
          }
        }
      ],
      "index": null,
      "attribute": {
        "id": 12,
        "isDelete": 0,
        "createdTime": "2019-12-12T08:44:01.000+0000",
        "createdBy": "1",
        "updateTime": "2019-12-10T15:52:23.000+0000",
        "updateBy": "1",
        "pageNum": null,
        "pageSize": null,
        "cateCode": "024cd6bf1b2211eaa870005056c00001",
        "cateName": "传记",
        "parentCateCode": "0",
        "level": 1,
        "remark": "4",
        "frontCateCode": null,
        "parentCateCodeName": null,
        "goods": null,
        "cateList": null
      }
    },
    {
      "nodeName": "青春文学",
      "nodeId": "30bf52a71b2211eaa870005056c00001",
      "childNode": [
        {
          "nodeName": "古代言情",
          "nodeId": "384f14701b2211eaa870005056c00001",
          "childNode": null,
          "index": null,
          "attribute": {
            "id": 16,
            "isDelete": 0,
            "createdTime": "2019-12-10T15:53:54.000+0000",
            "createdBy": "1",
            "updateTime": "2019-12-10T15:53:54.000+0000",
            "updateBy": "1",
            "pageNum": null,
            "pageSize": null,
            "cateCode": "384f14701b2211eaa870005056c00001",
            "cateName": "古代言情",
            "parentCateCode": "30bf52a71b2211eaa870005056c00001",
            "level": 2,
            "remark": "5-1",
            "frontCateCode": null,
            "parentCateCodeName": null,
            "goods": null,
            "cateList": null
          }
        },
        {
          "nodeName": "现代言情",
          "nodeId": "45471ab21b2211eaa870005056c00001",
          "childNode": null,
          "index": null,
          "attribute": {
            "id": 17,
            "isDelete": 0,
            "createdTime": "2019-12-10T15:54:16.000+0000",
            "createdBy": "1",
            "updateTime": "2019-12-10T15:54:16.000+0000",
            "updateBy": "1",
            "pageNum": null,
            "pageSize": null,
            "cateCode": "45471ab21b2211eaa870005056c00001",
            "cateName": "现代言情",
            "parentCateCode": "30bf52a71b2211eaa870005056c00001",
            "level": 2,
            "remark": "5-2",
            "frontCateCode": null,
            "parentCateCodeName": null,
            "goods": null,
            "cateList": null
          }
        }
      ],
      "index": null,
      "attribute": {
        "id": 15,
        "isDelete": 0,
        "createdTime": "2019-12-10T15:53:41.000+0000",
        "createdBy": "1",
        "updateTime": "2019-12-10T15:53:41.000+0000",
        "updateBy": "1",
        "pageNum": null,
        "pageSize": null,
        "cateCode": "30bf52a71b2211eaa870005056c00001",
        "cateName": "青春文学",
        "parentCateCode": "0",
        "level": 1,
        "remark": "5",
        "frontCateCode": null,
        "parentCateCodeName": null,
        "goods": null,
        "cateList": null
      }
    },
    {
      "nodeName": "科普百科",
      "nodeId": "593c0b3f1b2211eaa870005056c00001",
      "childNode": [
        {
          "nodeName": "亲近自然",
          "nodeId": "64873aff1b2211eaa870005056c00001",
          "childNode": null,
          "index": null,
          "attribute": {
            "id": 19,
            "isDelete": 0,
            "createdTime": "2019-12-10T15:55:08.000+0000",
            "createdBy": "1",
            "updateTime": "2019-12-10T15:55:08.000+0000",
            "updateBy": "1",
            "pageNum": null,
            "pageSize": null,
            "cateCode": "64873aff1b2211eaa870005056c00001",
            "cateName": "亲近自然",
            "parentCateCode": "593c0b3f1b2211eaa870005056c00001",
            "level": 2,
            "remark": "6-1",
            "frontCateCode": null,
            "parentCateCodeName": null,
            "goods": null,
            "cateList": null
          }
        },
        {
          "nodeName": "科学漫画",
          "nodeId": "7038a2661b2211eaa870005056c00001",
          "childNode": null,
          "index": null,
          "attribute": {
            "id": 20,
            "isDelete": 0,
            "createdTime": "2019-12-10T15:55:28.000+0000",
            "createdBy": "1",
            "updateTime": "2019-12-10T15:55:28.000+0000",
            "updateBy": "1",
            "pageNum": null,
            "pageSize": null,
            "cateCode": "7038a2661b2211eaa870005056c00001",
            "cateName": "科学漫画",
            "parentCateCode": "593c0b3f1b2211eaa870005056c00001",
            "level": 2,
            "remark": "6-2",
            "frontCateCode": null,
            "parentCateCodeName": null,
            "goods": null,
            "cateList": null
          }
        },
        {
          "nodeName": "地理百科",
          "nodeId": "80fa32591b2211eaa870005056c00001",
          "childNode": null,
          "index": null,
          "attribute": {
            "id": 21,
            "isDelete": 0,
            "createdTime": "2019-12-10T15:55:56.000+0000",
            "createdBy": "1",
            "updateTime": "2019-12-10T15:55:56.000+0000",
            "updateBy": "1",
            "pageNum": null,
            "pageSize": null,
            "cateCode": "80fa32591b2211eaa870005056c00001",
            "cateName": "地理百科",
            "parentCateCode": "593c0b3f1b2211eaa870005056c00001",
            "level": 2,
            "remark": "6-3",
            "frontCateCode": null,
            "parentCateCodeName": null,
            "goods": null,
            "cateList": null
          }
        }
      ],
      "index": null,
      "attribute": {
        "id": 18,
        "isDelete": 0,
        "createdTime": "2019-12-10T15:54:49.000+0000",
        "createdBy": "1",
        "updateTime": "2019-12-10T15:54:49.000+0000",
        "updateBy": "1",
        "pageNum": null,
        "pageSize": null,
        "cateCode": "593c0b3f1b2211eaa870005056c00001",
        "cateName": "科普百科",
        "parentCateCode": "0",
        "level": 1,
        "remark": "6",
        "frontCateCode": null,
        "parentCateCodeName": null,
        "goods": null,
        "cateList": null
      }
    },
    {
      "nodeName": "社会科学",
      "nodeId": "1e577bd41bbe11eaa870005056c00001",
      "childNode": [
        {
          "nodeName": "社会学",
          "nodeId": "327874651bbe11eaa870005056c00001",
          "childNode": null,
          "index": null,
          "attribute": {
            "id": 23,
            "isDelete": 0,
            "createdTime": "2019-12-11T10:30:25.000+0000",
            "createdBy": "1",
            "updateTime": "2019-12-11T10:30:25.000+0000",
            "updateBy": "1",
            "pageNum": null,
            "pageSize": null,
            "cateCode": "327874651bbe11eaa870005056c00001",
            "cateName": "社会学",
            "parentCateCode": "1e577bd41bbe11eaa870005056c00001",
            "level": 2,
            "remark": "7-1",
            "frontCateCode": null,
            "parentCateCodeName": null,
            "goods": null,
            "cateList": null
          }
        },
        {
          "nodeName": "人类学",
          "nodeId": "3938e7241bbe11eaa870005056c00001",
          "childNode": null,
          "index": null,
          "attribute": {
            "id": 24,
            "isDelete": 0,
            "createdTime": "2019-12-11T10:30:36.000+0000",
            "createdBy": "1",
            "updateTime": "2019-12-11T10:30:36.000+0000",
            "updateBy": "1",
            "pageNum": null,
            "pageSize": null,
            "cateCode": "3938e7241bbe11eaa870005056c00001",
            "cateName": "人类学",
            "parentCateCode": "1e577bd41bbe11eaa870005056c00001",
            "level": 2,
            "remark": "7-2",
            "frontCateCode": null,
            "parentCateCodeName": null,
            "goods": null,
            "cateList": null
          }
        }
      ],
      "index": null,
      "attribute": {
        "id": 22,
        "isDelete": 0,
        "createdTime": "2019-12-11T10:30:00.000+0000",
        "createdBy": "1",
        "updateTime": "2019-12-11T10:29:51.000+0000",
        "updateBy": "1",
        "pageNum": null,
        "pageSize": null,
        "cateCode": "1e577bd41bbe11eaa870005056c00001",
        "cateName": "社会科学",
        "parentCateCode": "0",
        "level": 1,
        "remark": "7",
        "frontCateCode": null,
        "parentCateCodeName": null,
        "goods": null,
        "cateList": null
      }
    },
    {
      "nodeName": "外语学习",
      "nodeId": "4a5905781bbe11eaa870005056c00001",
      "childNode": [
        {
          "nodeName": "英语读物",
          "nodeId": "50948a211bbe11eaa870005056c00001",
          "childNode": null,
          "index": null,
          "attribute": {
            "id": 26,
            "isDelete": 0,
            "createdTime": "2019-12-11T10:31:15.000+0000",
            "createdBy": "1",
            "updateTime": "2019-12-11T10:31:15.000+0000",
            "updateBy": "1",
            "pageNum": null,
            "pageSize": null,
            "cateCode": "50948a211bbe11eaa870005056c00001",
            "cateName": "英语读物",
            "parentCateCode": "4a5905781bbe11eaa870005056c00001",
            "level": 2,
            "remark": "8-1",
            "frontCateCode": null,
            "parentCateCodeName": null,
            "goods": null,
            "cateList": null
          }
        },
        {
          "nodeName": "英语口语",
          "nodeId": "5cc7efca1bbe11eaa870005056c00001",
          "childNode": null,
          "index": null,
          "attribute": {
            "id": 27,
            "isDelete": 0,
            "createdTime": "2019-12-11T10:31:36.000+0000",
            "createdBy": "1",
            "updateTime": "2019-12-11T10:31:36.000+0000",
            "updateBy": "1",
            "pageNum": null,
            "pageSize": null,
            "cateCode": "5cc7efca1bbe11eaa870005056c00001",
            "cateName": "英语口语",
            "parentCateCode": "4a5905781bbe11eaa870005056c00001",
            "level": 2,
            "remark": "8-2",
            "frontCateCode": null,
            "parentCateCodeName": null,
            "goods": null,
            "cateList": null
          }
        },
        {
          "nodeName": "四六级",
          "nodeId": "759288291bbe11eaa870005056c00001",
          "childNode": null,
          "index": null,
          "attribute": {
            "id": 28,
            "isDelete": 0,
            "createdTime": "2019-12-11T10:32:17.000+0000",
            "createdBy": "1",
            "updateTime": "2019-12-11T10:32:17.000+0000",
            "updateBy": "1",
            "pageNum": null,
            "pageSize": null,
            "cateCode": "759288291bbe11eaa870005056c00001",
            "cateName": "四六级",
            "parentCateCode": "4a5905781bbe11eaa870005056c00001",
            "level": 2,
            "remark": "8-3",
            "frontCateCode": null,
            "parentCateCodeName": null,
            "goods": null,
            "cateList": null
          }
        }
      ],
      "index": null,
      "attribute": {
        "id": 25,
        "isDelete": 0,
        "createdTime": "2019-12-11T10:31:05.000+0000",
        "createdBy": "1",
        "updateTime": "2019-12-11T10:31:05.000+0000",
        "updateBy": "1",
        "pageNum": null,
        "pageSize": null,
        "cateCode": "4a5905781bbe11eaa870005056c00001",
        "cateName": "外语学习",
        "parentCateCode": "0",
        "level": 1,
        "remark": "8",
        "frontCateCode": null,
        "parentCateCodeName": null,
        "goods": null,
        "cateList": null
      }
    },
    {
      "nodeName": "法律",
      "nodeId": "8198ac3d1bbe11eaa870005056c00001",
      "childNode": [
        {
          "nodeName": "司法考试",
          "nodeId": "8ccf7c011bbe11eaa870005056c00001",
          "childNode": null,
          "index": null,
          "attribute": {
            "id": 30,
            "isDelete": 0,
            "createdTime": "2019-12-11T10:32:56.000+0000",
            "createdBy": "1",
            "updateTime": "2019-12-11T10:32:56.000+0000",
            "updateBy": "1",
            "pageNum": null,
            "pageSize": null,
            "cateCode": "8ccf7c011bbe11eaa870005056c00001",
            "cateName": "司法考试",
            "parentCateCode": "8198ac3d1bbe11eaa870005056c00001",
            "level": 2,
            "remark": "9-1",
            "frontCateCode": null,
            "parentCateCodeName": null,
            "goods": null,
            "cateList": null
          }
        },
        {
          "nodeName": "经典著作",
          "nodeId": "92de62e11bbe11eaa870005056c00001",
          "childNode": null,
          "index": null,
          "attribute": {
            "id": 31,
            "isDelete": 0,
            "createdTime": "2019-12-11T10:33:06.000+0000",
            "createdBy": "1",
            "updateTime": "2019-12-11T10:33:06.000+0000",
            "updateBy": "1",
            "pageNum": null,
            "pageSize": null,
            "cateCode": "92de62e11bbe11eaa870005056c00001",
            "cateName": "经典著作",
            "parentCateCode": "8198ac3d1bbe11eaa870005056c00001",
            "level": 2,
            "remark": "9-2",
            "frontCateCode": null,
            "parentCateCodeName": null,
            "goods": null,
            "cateList": null
          }
        },
        {
          "nodeName": "法律法规",
          "nodeId": "9d5585071bbe11eaa870005056c00001",
          "childNode": null,
          "index": null,
          "attribute": {
            "id": 32,
            "isDelete": 0,
            "createdTime": "2019-12-11T10:33:24.000+0000",
            "createdBy": "1",
            "updateTime": "2019-12-11T10:33:24.000+0000",
            "updateBy": "1",
            "pageNum": null,
            "pageSize": null,
            "cateCode": "9d5585071bbe11eaa870005056c00001",
            "cateName": "法律法规",
            "parentCateCode": "8198ac3d1bbe11eaa870005056c00001",
            "level": 2,
            "remark": "9-3",
            "frontCateCode": null,
            "parentCateCodeName": null,
            "goods": null,
            "cateList": null
          }
        }
      ],
      "index": null,
      "attribute": {
        "id": 29,
        "isDelete": 0,
        "createdTime": "2019-12-11T10:32:37.000+0000",
        "createdBy": "1",
        "updateTime": "2019-12-11T10:32:37.000+0000",
        "updateBy": "1",
        "pageNum": null,
        "pageSize": null,
        "cateCode": "8198ac3d1bbe11eaa870005056c00001",
        "cateName": "法律",
        "parentCateCode": "0",
        "level": 1,
        "remark": "9",
        "frontCateCode": null,
        "parentCateCodeName": null,
        "goods": null,
        "cateList": null
      }
    },
    {
      "nodeName": "烹饪美食",
      "nodeId": "c24fb11f1bbe11eaa870005056c00001",
      "childNode": [
        {
          "nodeName": "烘焙甜品",
          "nodeId": "d01b34831bbe11eaa870005056c00001",
          "childNode": null,
          "index": null,
          "attribute": {
            "id": 34,
            "isDelete": 0,
            "createdTime": "2019-12-11T10:34:49.000+0000",
            "createdBy": "1",
            "updateTime": "2019-12-11T10:34:49.000+0000",
            "updateBy": "1",
            "pageNum": null,
            "pageSize": null,
            "cateCode": "d01b34831bbe11eaa870005056c00001",
            "cateName": "烘焙甜品",
            "parentCateCode": "c24fb11f1bbe11eaa870005056c00001",
            "level": 2,
            "remark": "10-1",
            "frontCateCode": null,
            "parentCateCodeName": null,
            "goods": null,
            "cateList": null
          }
        },
        {
          "nodeName": "家常菜谱",
          "nodeId": "d7f60f751bbe11eaa870005056c00001",
          "childNode": null,
          "index": null,
          "attribute": {
            "id": 35,
            "isDelete": 0,
            "createdTime": "2019-12-11T10:35:02.000+0000",
            "createdBy": "1",
            "updateTime": "2019-12-11T10:35:02.000+0000",
            "updateBy": "1",
            "pageNum": null,
            "pageSize": null,
            "cateCode": "d7f60f751bbe11eaa870005056c00001",
            "cateName": "家常菜谱",
            "parentCateCode": "c24fb11f1bbe11eaa870005056c00001",
            "level": 2,
            "remark": "10-2",
            "frontCateCode": null,
            "parentCateCodeName": null,
            "goods": null,
            "cateList": null
          }
        }
      ],
      "index": null,
      "attribute": {
        "id": 33,
        "isDelete": 0,
        "createdTime": "2019-12-11T10:34:26.000+0000",
        "createdBy": "1",
        "updateTime": "2019-12-11T10:34:26.000+0000",
        "updateBy": "1",
        "pageNum": null,
        "pageSize": null,
        "cateCode": "c24fb11f1bbe11eaa870005056c00001",
        "cateName": "烹饪美食",
        "parentCateCode": "0",
        "level": 1,
        "remark": "10",
        "frontCateCode": null,
        "parentCateCodeName": null,
        "goods": null,
        "cateList": null
      }
    },
    {
      "nodeName": "绘画",
      "nodeId": "e4baa95f1bbe11eaa870005056c00001",
      "childNode": [
        {
          "nodeName": "名家画集",
          "nodeId": "ed6a7d111bbe11eaa870005056c00001",
          "childNode": null,
          "index": null,
          "attribute": {
            "id": 37,
            "isDelete": 0,
            "createdTime": "2019-12-11T10:35:38.000+0000",
            "createdBy": "1",
            "updateTime": "2019-12-11T10:35:38.000+0000",
            "updateBy": "1",
            "pageNum": null,
            "pageSize": null,
            "cateCode": "ed6a7d111bbe11eaa870005056c00001",
            "cateName": "名家画集",
            "parentCateCode": "e4baa95f1bbe11eaa870005056c00001",
            "level": 2,
            "remark": "11-1",
            "frontCateCode": null,
            "parentCateCodeName": null,
            "goods": null,
            "cateList": null
          }
        },
        {
          "nodeName": "绘画技巧",
          "nodeId": "05cae51c1bbf11eaa870005056c00001",
          "childNode": null,
          "index": null,
          "attribute": {
            "id": 38,
            "isDelete": 0,
            "createdTime": "2019-12-11T10:36:19.000+0000",
            "createdBy": "1",
            "updateTime": "2019-12-11T10:36:19.000+0000",
            "updateBy": "1",
            "pageNum": null,
            "pageSize": null,
            "cateCode": "05cae51c1bbf11eaa870005056c00001",
            "cateName": "绘画技巧",
            "parentCateCode": "e4baa95f1bbe11eaa870005056c00001",
            "level": 2,
            "remark": "11-2",
            "frontCateCode": null,
            "parentCateCodeName": null,
            "goods": null,
            "cateList": null
          }
        }
      ],
      "index": null,
      "attribute": {
        "id": 36,
        "isDelete": 0,
        "createdTime": "2019-12-11T10:35:24.000+0000",
        "createdBy": "1",
        "updateTime": "2019-12-11T10:35:24.000+0000",
        "updateBy": "1",
        "pageNum": null,
        "pageSize": null,
        "cateCode": "e4baa95f1bbe11eaa870005056c00001",
        "cateName": "绘画",
        "parentCateCode": "0",
        "level": 1,
        "remark": "11",
        "frontCateCode": null,
        "parentCateCodeName": null,
        "goods": null,
        "cateList": null
      }
    },
    {
      "nodeName": "原版书",
      "nodeId": "1789c07e1bbf11eaa870005056c00001",
      "childNode": [
        {
          "nodeName": "英文原版",
          "nodeId": "24298aa51bbf11eaa870005056c00001",
          "childNode": null,
          "index": null,
          "attribute": {
            "id": 40,
            "isDelete": 0,
            "createdTime": "2019-12-11T10:37:10.000+0000",
            "createdBy": "1",
            "updateTime": "2019-12-11T10:37:10.000+0000",
            "updateBy": "1",
            "pageNum": null,
            "pageSize": null,
            "cateCode": "24298aa51bbf11eaa870005056c00001",
            "cateName": "英文原版",
            "parentCateCode": "1789c07e1bbf11eaa870005056c00001",
            "level": 2,
            "remark": "12-1",
            "frontCateCode": null,
            "parentCateCodeName": null,
            "goods": null,
            "cateList": null
          }
        },
        {
          "nodeName": "日文原版",
          "nodeId": "2ad704791bbf11eaa870005056c00001",
          "childNode": null,
          "index": null,
          "attribute": {
            "id": 41,
            "isDelete": 0,
            "createdTime": "2019-12-11T10:37:21.000+0000",
            "createdBy": "1",
            "updateTime": "2019-12-11T10:37:21.000+0000",
            "updateBy": "1",
            "pageNum": null,
            "pageSize": null,
            "cateCode": "2ad704791bbf11eaa870005056c00001",
            "cateName": "日文原版",
            "parentCateCode": "1789c07e1bbf11eaa870005056c00001",
            "level": 2,
            "remark": "12-2",
            "frontCateCode": null,
            "parentCateCodeName": null,
            "goods": null,
            "cateList": null
          }
        }
      ],
      "index": null,
      "attribute": {
        "id": 39,
        "isDelete": 0,
        "createdTime": "2019-12-11T10:36:49.000+0000",
        "createdBy": "1",
        "updateTime": "2019-12-11T10:36:49.000+0000",
        "updateBy": "1",
        "pageNum": null,
        "pageSize": null,
        "cateCode": "1789c07e1bbf11eaa870005056c00001",
        "cateName": "原版书",
        "parentCateCode": "0",
        "level": 1,
        "remark": "12",
        "frontCateCode": null,
        "parentCateCodeName": null,
        "goods": null,
        "cateList": null
      }
    },
    {
      "nodeName": "杂志期刊",
      "nodeId": "55d8d1a81bbf11eaa870005056c00001",
      "childNode": [
        {
          "nodeName": "时尚美妆",
          "nodeId": "656342701bbf11eaa870005056c00001",
          "childNode": null,
          "index": null,
          "attribute": {
            "id": 43,
            "isDelete": 0,
            "createdTime": "2019-12-11T10:39:00.000+0000",
            "createdBy": "1",
            "updateTime": "2019-12-11T10:39:00.000+0000",
            "updateBy": "1",
            "pageNum": null,
            "pageSize": null,
            "cateCode": "656342701bbf11eaa870005056c00001",
            "cateName": "时尚美妆",
            "parentCateCode": "55d8d1a81bbf11eaa870005056c00001",
            "level": 2,
            "remark": "13-1",
            "frontCateCode": null,
            "parentCateCodeName": null,
            "goods": null,
            "cateList": null
          }
        },
        {
          "nodeName": "文学文摘",
          "nodeId": "6f0b64d91bbf11eaa870005056c00001",
          "childNode": null,
          "index": null,
          "attribute": {
            "id": 44,
            "isDelete": 0,
            "createdTime": "2019-12-11T10:39:16.000+0000",
            "createdBy": "1",
            "updateTime": "2019-12-11T10:39:16.000+0000",
            "updateBy": "1",
            "pageNum": null,
            "pageSize": null,
            "cateCode": "6f0b64d91bbf11eaa870005056c00001",
            "cateName": "文学文摘",
            "parentCateCode": "55d8d1a81bbf11eaa870005056c00001",
            "level": 2,
            "remark": "13-2",
            "frontCateCode": null,
            "parentCateCodeName": null,
            "goods": null,
            "cateList": null
          }
        },
        {
          "nodeName": "旅游地理",
          "nodeId": "7a577dd91bbf11eaa870005056c00001",
          "childNode": null,
          "index": null,
          "attribute": {
            "id": 45,
            "isDelete": 0,
            "createdTime": "2019-12-11T10:39:35.000+0000",
            "createdBy": "1",
            "updateTime": "2019-12-11T10:39:35.000+0000",
            "updateBy": "1",
            "pageNum": null,
            "pageSize": null,
            "cateCode": "7a577dd91bbf11eaa870005056c00001",
            "cateName": "旅游地理",
            "parentCateCode": "55d8d1a81bbf11eaa870005056c00001",
            "level": 2,
            "remark": "13-3",
            "frontCateCode": null,
            "parentCateCodeName": null,
            "goods": null,
            "cateList": null
          }
        }
      ],
      "index": null,
      "attribute": {
        "id": 42,
        "isDelete": 0,
        "createdTime": "2019-12-11T10:38:34.000+0000",
        "createdBy": "1",
        "updateTime": "2019-12-11T10:38:34.000+0000",
        "updateBy": "1",
        "pageNum": null,
        "pageSize": null,
        "cateCode": "55d8d1a81bbf11eaa870005056c00001",
        "cateName": "杂志期刊",
        "parentCateCode": "0",
        "level": 1,
        "remark": "13",
        "frontCateCode": null,
        "parentCateCodeName": null,
        "goods": null,
        "cateList": null
      }
    }
  ],
  "msg": "查询成功",
  "code": 1,
  "success": true
}
